hwtools/__init__.py
hwtools/config_template.py
hwtools/config_tools.py
hwtools/data_manager.py
hwtools/log_config.py
hwtools/parser.py
hwtools/training_data_script.py
hwtools/ui_manager.py
hwtools/user_config.py
hwtools-0.0.1.dist-info/LICENSE.txt
hwtools-0.0.1.dist-info/METADATA
hwtools-0.0.1.dist-info/WHEEL
hwtools-0.0.1.dist-info/entry_points.txt
hwtools-0.0.1.dist-info/RECORD
