Metadata-Version: 2.1
Name: hwtools
Version: 0.0.1
Summary: A library to parse Handwritten Text.
License: MongoDB's Server Side Public License Version 1
Author: Gaël Cousin
Author-email: gcousin333@gmail.com
Requires-Python: >=3.10.6,<4.0.0
Classifier: License :: Other/Proprietary License
Classifier: Programming Language :: Python :: 3
Classifier: Programming Language :: Python :: 3.11
Requires-Dist: matplotlib (>=3.5.1,<4.0.0)
Requires-Dist: np-gui (>0.0.3,<1)
Requires-Dist: numba (>=0.56.4,<1)
Requires-Dist: numpy (>=1.21.0,<2.0.0)
Requires-Dist: scikit-image (>=0.19.3,<1)
